picotest
